general_superstaq/__init__.py
general_superstaq/_init_vars.py
general_superstaq/_version.py
general_superstaq/_version_test.py
general_superstaq/machine_api.py
general_superstaq/machine_api_test.py
general_superstaq/models.py
general_superstaq/models_test.py
general_superstaq/py.typed
general_superstaq/resource_estimate.py
general_superstaq/resource_estimate_test.py
general_superstaq/serialization.py
general_superstaq/serialization_test.py
general_superstaq/service.py
general_superstaq/service_test.py
general_superstaq/superstaq_client.py
general_superstaq/superstaq_client_test.py
general_superstaq/superstaq_exceptions.py
general_superstaq/superstaq_exceptions_test.py
general_superstaq/testing.py
general_superstaq/typing.py
general_superstaq/validation.py
general_superstaq/validation_test.py
general_superstaq/check/__init__.py
general_superstaq-0.5.61.dist-info/METADATA
general_superstaq-0.5.61.dist-info/WHEEL
general_superstaq-0.5.61.dist-info/top_level.txt
general_superstaq-0.5.61.dist-info/RECORD
